huaweicloudsdkmeeting/__init__.py
huaweicloudsdkmeeting/v1/__init__.py
huaweicloudsdkmeeting/v1/meeting_async_client.py
huaweicloudsdkmeeting/v1/meeting_client.py
huaweicloudsdkmeeting/v1/meeting_credentials.py
huaweicloudsdkmeeting/v1/model/__init__.py
huaweicloudsdkmeeting/v1/model/active_dto.py
huaweicloudsdkmeeting/v1/model/add_app_id_request.py
huaweicloudsdkmeeting/v1/model/add_app_id_request_body.py
huaweicloudsdkmeeting/v1/model/add_app_id_response.py
huaweicloudsdkmeeting/v1/model/add_corp_admin_request.py
huaweicloudsdkmeeting/v1/model/add_corp_admin_response.py
huaweicloudsdkmeeting/v1/model/add_corp_dto.py
huaweicloudsdkmeeting/v1/model/add_corp_request.py
huaweicloudsdkmeeting/v1/model/add_corp_res_dto.py
huaweicloudsdkmeeting/v1/model/add_corp_response.py
huaweicloudsdkmeeting/v1/model/add_department_request.py
huaweicloudsdkmeeting/v1/model/add_department_response.py
huaweicloudsdkmeeting/v1/model/add_device_dto.py
huaweicloudsdkmeeting/v1/model/add_device_request.py
huaweicloudsdkmeeting/v1/model/add_device_response.py
huaweicloudsdkmeeting/v1/model/add_material_request.py
huaweicloudsdkmeeting/v1/model/add_material_request_body.py
huaweicloudsdkmeeting/v1/model/add_material_response.py
huaweicloudsdkmeeting/v1/model/add_program_request.py
huaweicloudsdkmeeting/v1/model/add_program_response.py
huaweicloudsdkmeeting/v1/model/add_publication_request.py
huaweicloudsdkmeeting/v1/model/add_publication_response.py
huaweicloudsdkmeeting/v1/model/add_resource_request.py
huaweicloudsdkmeeting/v1/model/add_resource_response.py
huaweicloudsdkmeeting/v1/model/add_to_personal_space_request.py
huaweicloudsdkmeeting/v1/model/add_to_personal_space_response.py
huaweicloudsdkmeeting/v1/model/add_user_dto.py
huaweicloudsdkmeeting/v1/model/add_user_request.py
huaweicloudsdkmeeting/v1/model/add_user_request_body.py
huaweicloudsdkmeeting/v1/model/add_user_response.py
huaweicloudsdkmeeting/v1/model/admin_dto.py
huaweicloudsdkmeeting/v1/model/admin_reset_pwd_req_dto.py
huaweicloudsdkmeeting-3.1.184.dist-info/METADATA
huaweicloudsdkmeeting-3.1.184.dist-info/WHEEL
huaweicloudsdkmeeting-3.1.184.dist-info/licenses/LICENSE
huaweicloudsdkmeeting-3.1.184.dist-info/RECORD
